apiconnectors/__init__.py
apiconnectors/github/__init__.py
apiconnectors/github/client.py
apiconnectors/jira/__init__.py
apiconnectors/jira/jira_admin.py
apiconnectors/jira/jira_cloud.py
apiconnectors/ldap/__init__.py
apiconnectors/ldap/client.py
apiconnectors/mattermost/__init__.py
apiconnectors/mattermost/client.py
apiconnectors/vault/__init__.py
apiconnectors/vault/client.py
canonical_api_connectors-1.2.0.dist-info/LICENSE
canonical_api_connectors-1.2.0.dist-info/METADATA
canonical_api_connectors-1.2.0.dist-info/WHEEL
canonical_api_connectors-1.2.0.dist-info/RECORD
